py_redis_ds/__init__.py
py_redis_ds/builtins.py
py_redis_ds/collections.py
py_redis_ds/common.py
py_redis_ds/queue.py
py_redis_ds-0.0.1.dist-info/METADATA
py_redis_ds-0.0.1.dist-info/WHEEL
py_redis_ds-0.0.1.dist-info/licenses/LICENSE
py_redis_ds-0.0.1.dist-info/RECORD
