Metadata-Version: 2.4
Name: py-redis-ds
Version: 0.0.1
Summary: Drop-in replacements for Python data structures backed by Redis for shared access.
Project-URL: Homepage, https://github.com/bhavya-tech/python-redis-datastructures
Project-URL: Issues, https://github.com/bhavya-tech/python-redis-datastructures/issues
Author-email: Bhavya Peshavaria <bhavyapeshavaria@gmail.com>
License-File: LICENSE
Classifier: License :: OSI Approved :: MIT License
Classifier: Operating System :: OS Independent
Classifier: Programming Language :: Python :: 3
Requires-Python: >=3.8
Requires-Dist: redis>=5.2.1
